porto/__init__.py
porto/provider.py
porto/providers/internetmarke.py
porto-0.1.2.dist-info/LICENSE
porto-0.1.2.dist-info/WHEEL
porto-0.1.2.dist-info/METADATA
porto-0.1.2.dist-info/RECORD
